[
  {
    "patnerNumber": "551201615-6",
    "folderNumber": "151371648-4",
    "cuil": "20-12358495-3",
    "dni": "12358495",
    "status": false,
    "distribution": "398931188-3",
    "admissionDate": "10/20/2020",
    "comercializador": "Wain Haddick",
    "personalInfo": { "firstName": "Alizée", "lastName": "Haddick" },
    "paymentMethod": "cash"
  },
  {
    "patnerNumber": "640814351-2",
    "folderNumber": "389063870-8",
    "cuil": "20-12358495-3",
    "dni": "12358495",
    "status": false,
    "distribution": "784369594-X",
    "admissionDate": "9/28/2020",
    "comercializador": "Bonnie Swede",
    "personalInfo": { "firstName": "Torbjörn", "lastName": "Swede" },
    "paymentMethod": "cash"
  },
  {
    "patnerNumber": "446923258-0",
    "folderNumber": "539164824-6",
    "cuil": "20-12358495-3",
    "dni": "12358495",
    "status": false,
    "distribution": "932393138-1",
    "admissionDate": "10/14/2020",
    "comercializador": "Garwin Blood",
    "personalInfo": { "firstName": "Pélagie", "lastName": "Blood" },
    "paymentMethod": "cash"
  },
  {
    "patnerNumber": "917629573-7",
    "folderNumber": "679071203-8",
    "cuil": "20-12358495-3",
    "dni": "12358495",
    "status": false,
    "distribution": "540630726-6",
    "admissionDate": "6/20/2020",
    "comercializador": "Keefe Sarjent",
    "personalInfo": { "firstName": "Adèle", "lastName": "Sarjent" },
    "paymentMethod": "cash"
  },
  {
    "patnerNumber": "437834437-8",
    "folderNumber": "155235596-9",
    "cuil": "20-12358495-3",
    "dni": "12358495",
    "status": false,
    "distribution": "304497111-X",
    "admissionDate": "1/11/2020",
    "comercializador": "Gavin O'Cullinane",
    "personalInfo": { "firstName": "Bérengère", "lastName": "O'Cullinane" },
    "paymentMethod": "credit car"
  },
  {
    "patnerNumber": "889586355-0",
    "folderNumber": "774079431-7",
    "cuil": "20-12358495-3",
    "dni": "12358495",
    "status": true,
    "distribution": "491387333-4",
    "admissionDate": "12/25/2019",
    "comercializador": "Lina Emptage",
    "personalInfo": { "firstName": "Léandre", "lastName": "Emptage" },
    "paymentMethod": "cash"
  },
  {
    "patnerNumber": "987983683-9",
    "folderNumber": "081626488-0",
    "cuil": "20-12358495-3",
    "dni": "12358495",
    "status": false,
    "distribution": "278008999-7",
    "admissionDate": "4/17/2020",
    "comercializador": "Huntlee Stockow",
    "personalInfo": { "firstName": "Dorothée", "lastName": "Stockow" },
    "paymentMethod": "credit car"
  },
  {
    "patnerNumber": "770226287-7",
    "folderNumber": "224010453-8",
    "cuil": "20-12358495-3",
    "dni": "12358495",
    "status": false,
    "distribution": "863372386-7",
    "admissionDate": "12/30/2019",
    "comercializador": "Clyde Saffran",
    "personalInfo": { "firstName": "Crééz", "lastName": "Saffran" },
    "paymentMethod": "cash"
  },
  {
    "patnerNumber": "671199956-8",
    "folderNumber": "886956621-8",
    "cuil": "20-12358495-3",
    "dni": "12358495",
    "status": true,
    "distribution": "659594979-2",
    "admissionDate": "3/29/2020",
    "comercializador": "Allissa Hartop",
    "personalInfo": { "firstName": "Mårten", "lastName": "Hartop" },
    "paymentMethod": "credit car"
  },
  {
    "patnerNumber": "985849238-3",
    "folderNumber": "231799057-X",
    "cuil": "20-12358495-3",
    "dni": "12358495",
    "status": true,
    "distribution": "754551946-9",
    "admissionDate": "9/18/2020",
    "comercializador": "Horatia MacDunleavy",
    "personalInfo": { "firstName": "Tú", "lastName": "MacDunleavy" },
    "paymentMethod": "credit car"
  },
  {
    "patnerNumber": "814863885-3",
    "folderNumber": "269947982-9",
    "cuil": "20-12358495-3",
    "dni": "12358495",
    "status": true,
    "distribution": "351381875-0",
    "admissionDate": "10/21/2020",
    "comercializador": "Casey Ringrose",
    "personalInfo": { "firstName": "Jú", "lastName": "Ringrose" },
    "paymentMethod": "cash"
  },
  {
    "patnerNumber": "270020500-6",
    "folderNumber": "552420370-3",
    "cuil": "20-12358495-3",
    "dni": "12358495",
    "status": false,
    "distribution": "489605197-1",
    "admissionDate": "9/9/2020",
    "comercializador": "Dalila Scotchforth",
    "personalInfo": { "firstName": "Aloïs", "lastName": "Scotchforth" },
    "paymentMethod": "cash"
  },
  {
    "patnerNumber": "142019339-2",
    "folderNumber": "336065565-6",
    "cuil": "20-12358495-3",
    "dni": "12358495",
    "status": true,
    "distribution": "929615924-5",
    "admissionDate": "9/20/2020",
    "comercializador": "Coralie Paskerful",
    "personalInfo": { "firstName": "Laïla", "lastName": "Paskerful" },
    "paymentMethod": "credit car"
  },
  {
    "patnerNumber": "904919354-4",
    "folderNumber": "319166563-3",
    "cuil": "20-12358495-3",
    "dni": "12358495",
    "status": true,
    "distribution": "085830206-3",
    "admissionDate": "4/2/2020",
    "comercializador": "Rayshell Hariot",
    "personalInfo": { "firstName": "Bécassine", "lastName": "Hariot" },
    "paymentMethod": "credit car"
  },
  {
    "patnerNumber": "496483010-1",
    "folderNumber": "514005104-4",
    "cuil": "20-12358495-3",
    "dni": "12358495",
    "status": false,
    "distribution": "793739187-1",
    "admissionDate": "6/27/2020",
    "comercializador": "Cathleen Bouldstridge",
    "personalInfo": { "firstName": "Anaëlle", "lastName": "Bouldstridge" },
    "paymentMethod": "credit car"
  },
  {
    "patnerNumber": "755503281-3",
    "folderNumber": "687306045-3",
    "cuil": "20-12358495-3",
    "dni": "12358495",
    "status": true,
    "distribution": "786716239-9",
    "admissionDate": "1/11/2020",
    "comercializador": "Bank Ingarfield",
    "personalInfo": { "firstName": "Illustrée", "lastName": "Ingarfield" },
    "paymentMethod": "credit car"
  },
  {
    "patnerNumber": "295153275-X",
    "folderNumber": "884901906-8",
    "cuil": "20-12358495-3",
    "dni": "12358495",
    "status": false,
    "distribution": "867688907-4",
    "admissionDate": "3/12/2020",
    "comercializador": "Gusti Skillanders",
    "personalInfo": { "firstName": "Mahélie", "lastName": "Skillanders" },
    "paymentMethod": "credit car"
  },
  {
    "patnerNumber": "943839554-7",
    "folderNumber": "806192680-6",
    "cuil": "20-12358495-3",
    "dni": "12358495",
    "status": false,
    "distribution": "629505949-X",
    "admissionDate": "1/8/2020",
    "comercializador": "Ynes Bartod",
    "personalInfo": { "firstName": "Gaëlle", "lastName": "Bartod" },
    "paymentMethod": "cash"
  },
  {
    "patnerNumber": "240101268-0",
    "folderNumber": "957529941-8",
    "cuil": "20-12358495-3",
    "dni": "12358495",
    "status": true,
    "distribution": "758449264-9",
    "admissionDate": "4/23/2020",
    "comercializador": "Florida Grimolbie",
    "personalInfo": { "firstName": "Mélanie", "lastName": "Grimolbie" },
    "paymentMethod": "credit car"
  },
  {
    "patnerNumber": "723318778-9",
    "folderNumber": "705604886-2",
    "cuil": "20-12358495-3",
    "dni": "12358495",
    "status": false,
    "distribution": "703525779-9",
    "admissionDate": "1/6/2020",
    "comercializador": "Yehudit Heintz",
    "personalInfo": { "firstName": "Anaïs", "lastName": "Heintz" },
    "paymentMethod": "credit car"
  },
  {
    "patnerNumber": "824833283-7",
    "folderNumber": "785710100-1",
    "cuil": "20-12358495-3",
    "dni": "12358495",
    "status": true,
    "distribution": "576932256-X",
    "admissionDate": "6/11/2020",
    "comercializador": "Jordana Bumpass",
    "personalInfo": { "firstName": "Maëlann", "lastName": "Bumpass" },
    "paymentMethod": "cash"
  },
  {
    "patnerNumber": "837310878-5",
    "folderNumber": "585795341-3",
    "cuil": "20-12358495-3",
    "dni": "12358495",
    "status": false,
    "distribution": "729066304-7",
    "admissionDate": "6/11/2020",
    "comercializador": "Jaquith Wrathmall",
    "personalInfo": { "firstName": "Médiamass", "lastName": "Wrathmall" },
    "paymentMethod": "cash"
  },
  {
    "patnerNumber": "044724498-1",
    "folderNumber": "821653952-5",
    "cuil": "20-12358495-3",
    "dni": "12358495",
    "status": false,
    "distribution": "079281545-9",
    "admissionDate": "7/23/2020",
    "comercializador": "Twila De Carteret",
    "personalInfo": { "firstName": "Audréanne", "lastName": "De Carteret" },
    "paymentMethod": "credit car"
  },
  {
    "patnerNumber": "921577236-7",
    "folderNumber": "880025652-X",
    "cuil": "20-12358495-3",
    "dni": "12358495",
    "status": true,
    "distribution": "006758384-9",
    "admissionDate": "5/16/2020",
    "comercializador": "Sigfried Jeavons",
    "personalInfo": { "firstName": "Garçon", "lastName": "Jeavons" },
    "paymentMethod": "cash"
  },
  {
    "patnerNumber": "044321351-8",
    "folderNumber": "577908806-3",
    "cuil": "20-12358495-3",
    "dni": "12358495",
    "status": true,
    "distribution": "340048386-9",
    "admissionDate": "10/4/2020",
    "comercializador": "Krysta Izzatt",
    "personalInfo": { "firstName": "Mà", "lastName": "Izzatt" },
    "paymentMethod": "credit car"
  },
  {
    "patnerNumber": "035521566-7",
    "folderNumber": "191495356-8",
    "cuil": "20-12358495-3",
    "dni": "12358495",
    "status": true,
    "distribution": "120482864-4",
    "admissionDate": "9/23/2020",
    "comercializador": "Hernando Carroll",
    "personalInfo": { "firstName": "Renée", "lastName": "Carroll" },
    "paymentMethod": "credit car"
  },
  {
    "patnerNumber": "399488797-6",
    "folderNumber": "430901586-7",
    "cuil": "20-12358495-3",
    "dni": "12358495",
    "status": true,
    "distribution": "689239537-6",
    "admissionDate": "5/9/2020",
    "comercializador": "Lou Leicester",
    "personalInfo": { "firstName": "Laurène", "lastName": "Leicester" },
    "paymentMethod": "cash"
  },
  {
    "patnerNumber": "537505815-4",
    "folderNumber": "456588909-9",
    "cuil": "20-12358495-3",
    "dni": "12358495",
    "status": true,
    "distribution": "175878080-0",
    "admissionDate": "12/8/2019",
    "comercializador": "Pearle Kegley",
    "personalInfo": { "firstName": "Lucrèce", "lastName": "Kegley" },
    "paymentMethod": "credit car"
  },
  {
    "patnerNumber": "987684986-7",
    "folderNumber": "719479312-1",
    "cuil": "20-12358495-3",
    "dni": "12358495",
    "status": false,
    "distribution": "616097835-7",
    "admissionDate": "8/13/2020",
    "comercializador": "Roi Spawton",
    "personalInfo": { "firstName": "Inès", "lastName": "Spawton" },
    "paymentMethod": "cash"
  },
  {
    "patnerNumber": "326412690-7",
    "folderNumber": "747823830-0",
    "cuil": "20-12358495-3",
    "dni": "12358495",
    "status": true,
    "distribution": "816623181-6",
    "admissionDate": "8/19/2020",
    "comercializador": "Ynes Tinn",
    "personalInfo": { "firstName": "Mà", "lastName": "Tinn" },
    "paymentMethod": "cash"
  },
  {
    "patnerNumber": "808490929-0",
    "folderNumber": "062211743-2",
    "cuil": "20-12358495-3",
    "dni": "12358495",
    "status": false,
    "distribution": "897195468-X",
    "admissionDate": "5/19/2020",
    "comercializador": "Lorelle Mulryan",
    "personalInfo": { "firstName": "Adèle", "lastName": "Mulryan" },
    "paymentMethod": "credit car"
  },
  {
    "patnerNumber": "670538027-6",
    "folderNumber": "623595924-9",
    "cuil": "20-12358495-3",
    "dni": "12358495",
    "status": false,
    "distribution": "274696066-4",
    "admissionDate": "4/13/2020",
    "comercializador": "Coreen Childes",
    "personalInfo": { "firstName": "Åke", "lastName": "Childes" },
    "paymentMethod": "credit car"
  },
  {
    "patnerNumber": "278948815-0",
    "folderNumber": "295796577-1",
    "cuil": "20-12358495-3",
    "dni": "12358495",
    "status": true,
    "distribution": "649289319-0",
    "admissionDate": "10/5/2020",
    "comercializador": "Diann Walasik",
    "personalInfo": { "firstName": "Aimée", "lastName": "Walasik" },
    "paymentMethod": "credit car"
  },
  {
    "patnerNumber": "291650082-0",
    "folderNumber": "052404646-8",
    "cuil": "20-12358495-3",
    "dni": "12358495",
    "status": true,
    "distribution": "216407387-8",
    "admissionDate": "1/23/2020",
    "comercializador": "Sharyl Anderbrugge",
    "personalInfo": { "firstName": "Rébecca", "lastName": "Anderbrugge" },
    "paymentMethod": "credit car"
  },
  {
    "patnerNumber": "096904071-7",
    "folderNumber": "899169981-2",
    "cuil": "20-12358495-3",
    "dni": "12358495",
    "status": true,
    "distribution": "854682355-3",
    "admissionDate": "11/17/2019",
    "comercializador": "Meier Kitcat",
    "personalInfo": { "firstName": "Mélanie", "lastName": "Kitcat" },
    "paymentMethod": "credit car"
  },
  {
    "patnerNumber": "789829460-2",
    "folderNumber": "632232847-6",
    "cuil": "20-12358495-3",
    "dni": "12358495",
    "status": true,
    "distribution": "370238482-0",
    "admissionDate": "11/13/2020",
    "comercializador": "Gilda Fautly",
    "personalInfo": { "firstName": "Kallisté", "lastName": "Fautly" },
    "paymentMethod": "credit car"
  },
  {
    "patnerNumber": "032049098-X",
    "folderNumber": "049577661-0",
    "cuil": "20-12358495-3",
    "dni": "12358495",
    "status": false,
    "distribution": "874286493-3",
    "admissionDate": "6/14/2020",
    "comercializador": "Alonso Massei",
    "personalInfo": { "firstName": "Gaëlle", "lastName": "Massei" },
    "paymentMethod": "credit car"
  },
  {
    "patnerNumber": "591483503-8",
    "folderNumber": "054081092-4",
    "cuil": "20-12358495-3",
    "dni": "12358495",
    "status": true,
    "distribution": "483172911-6",
    "admissionDate": "1/21/2020",
    "comercializador": "Fania Capstaff",
    "personalInfo": { "firstName": "Märta", "lastName": "Capstaff" },
    "paymentMethod": "credit car"
  },
  {
    "patnerNumber": "490913821-8",
    "folderNumber": "899967386-3",
    "cuil": "20-12358495-3",
    "dni": "12358495",
    "status": true,
    "distribution": "595091361-2",
    "admissionDate": "12/17/2019",
    "comercializador": "Jeno Cammoile",
    "personalInfo": { "firstName": "Almérinda", "lastName": "Cammoile" },
    "paymentMethod": "credit car"
  },
  {
    "patnerNumber": "468331955-1",
    "folderNumber": "845717994-2",
    "cuil": "20-12358495-3",
    "dni": "12358495",
    "status": true,
    "distribution": "748723728-1",
    "admissionDate": "2/27/2020",
    "comercializador": "Damara Fransman",
    "personalInfo": { "firstName": "Maëlann", "lastName": "Fransman" },
    "paymentMethod": "cash"
  },
  {
    "patnerNumber": "061715562-3",
    "folderNumber": "687007560-3",
    "cuil": "20-12358495-3",
    "dni": "12358495",
    "status": true,
    "distribution": "894346914-4",
    "admissionDate": "10/23/2020",
    "comercializador": "Karlee Silcocks",
    "personalInfo": { "firstName": "Daphnée", "lastName": "Silcocks" },
    "paymentMethod": "cash"
  },
  {
    "patnerNumber": "770058331-5",
    "folderNumber": "380421418-5",
    "cuil": "20-12358495-3",
    "dni": "12358495",
    "status": true,
    "distribution": "350608974-9",
    "admissionDate": "6/22/2020",
    "comercializador": "Clarke Lansdale",
    "personalInfo": { "firstName": "Maïwenn", "lastName": "Lansdale" },
    "paymentMethod": "cash"
  },
  {
    "patnerNumber": "429519928-1",
    "folderNumber": "347196719-2",
    "cuil": "20-12358495-3",
    "dni": "12358495",
    "status": true,
    "distribution": "720394131-0",
    "admissionDate": "4/10/2020",
    "comercializador": "Alanson Lorenzin",
    "personalInfo": { "firstName": "Aloïs", "lastName": "Lorenzin" },
    "paymentMethod": "cash"
  },
  {
    "patnerNumber": "536560624-8",
    "folderNumber": "513776141-9",
    "cuil": "20-12358495-3",
    "dni": "12358495",
    "status": false,
    "distribution": "509367429-X",
    "admissionDate": "3/22/2020",
    "comercializador": "Ardisj Christal",
    "personalInfo": { "firstName": "Björn", "lastName": "Christal" },
    "paymentMethod": "credit car"
  },
  {
    "patnerNumber": "698236202-7",
    "folderNumber": "440547263-7",
    "cuil": "20-12358495-3",
    "dni": "12358495",
    "status": true,
    "distribution": "512555331-X",
    "admissionDate": "9/16/2020",
    "comercializador": "Carmine Macallam",
    "personalInfo": { "firstName": "Judicaël", "lastName": "Macallam" },
    "paymentMethod": "cash"
  },
  {
    "patnerNumber": "010030229-7",
    "folderNumber": "089222940-3",
    "cuil": "20-12358495-3",
    "dni": "12358495",
    "status": true,
    "distribution": "432699672-2",
    "admissionDate": "4/18/2020",
    "comercializador": "Keith Rackstraw",
    "personalInfo": { "firstName": "Almérinda", "lastName": "Rackstraw" },
    "paymentMethod": "credit car"
  },
  {
    "patnerNumber": "009614526-9",
    "folderNumber": "954462434-1",
    "cuil": "20-12358495-3",
    "dni": "12358495",
    "status": false,
    "distribution": "353575697-9",
    "admissionDate": "10/23/2020",
    "comercializador": "Filip Jelk",
    "personalInfo": { "firstName": "Géraldine", "lastName": "Jelk" },
    "paymentMethod": "credit car"
  },
  {
    "patnerNumber": "230340345-6",
    "folderNumber": "952260097-0",
    "cuil": "20-12358495-3",
    "dni": "12358495",
    "status": true,
    "distribution": "009420440-3",
    "admissionDate": "4/7/2020",
    "comercializador": "Adele Chesnut",
    "personalInfo": { "firstName": "Athéna", "lastName": "Chesnut" },
    "paymentMethod": "credit car"
  },
  {
    "patnerNumber": "672343729-2",
    "folderNumber": "520264927-4",
    "cuil": "20-12358495-3",
    "dni": "12358495",
    "status": false,
    "distribution": "748285598-X",
    "admissionDate": "2/20/2020",
    "comercializador": "Crissie Vasyukov",
    "personalInfo": { "firstName": "Chloé", "lastName": "Vasyukov" },
    "paymentMethod": "credit car"
  },
  {
    "patnerNumber": "255062666-4",
    "folderNumber": "102694453-8",
    "cuil": "20-12358495-3",
    "dni": "12358495",
    "status": true,
    "distribution": "026270642-3",
    "admissionDate": "3/1/2020",
    "comercializador": "Almira Cadamy",
    "personalInfo": { "firstName": "Françoise", "lastName": "Cadamy" },
    "paymentMethod": "cash"
  }
]
